lovelyfi/__init__.py
lovelyfi/lwconfig.json
lovelyfi/lwrun.py
lovelyfi/lib/__init__.py
lovelyfi/lib/liblw.py
lovelyfi-0.0.1.dist-info/entry_points.txt
lovelyfi-0.0.1.dist-info/WHEEL
lovelyfi-0.0.1.dist-info/METADATA
lovelyfi-0.0.1.dist-info/RECORD
