Metadata-Version: 2.1
Name: lovelyfi
Version: 0.0.1
Summary: This is automatic wifi handler tool for particularly LPU wifi.
Home-page: https://github.com/PaperNova/lovelyfi
Author: PaperNova
Author-email: 0x0is1@protonmail.com
Requires-Python: >=3.7
Classifier: Intended Audience :: End Users/Desktop
Classifier: License :: OSI Approved :: MIT License
Classifier: Programming Language :: Python :: 3
Requires-Dist: requests
Requires-Dist: flit ; extra == "dev"
Provides-Extra: dev
